dpo/__init__.py
dpo/architecture/__init__.py
dpo/architecture/gene.py
dpo/architecture/backup/__init__.py
dpo/architecture/backup/gene.py
dpo/benchmarks/__init__.py
dpo/benchmarks/comprehensive_evaluation.py
dpo/benchmarks/hpobench_wrapper.py
dpo/benchmarks/nasbench101_wrapper.py
dpo/benchmarks/nasbench201_wrapper.py
dpo/benchmarks/nasbench301_wrapper.py
dpo/benchmarks/nats_bench_wrapper.py
dpo/constraints/__init__.py
dpo/constraints/handler.py
dpo/constraints/backup/__init__.py
dpo/constraints/backup/handler.py
dpo/core/__init__.py
dpo/core/agent.py
dpo/core/config.py
dpo/core/optimizer.py
dpo/core/backup/__init__.py
dpo/core/backup/agent copy.py
dpo/core/backup/config copy.py
dpo/core/backup/optimizer copy.py
dpo/evaluation/__init__.py
dpo/evaluation/cache.py
dpo/evaluation/ensemble.py
dpo/evaluation/estimators.py
dpo/evaluation/backup/__init__.py
dpo/evaluation/backup/cache copy.py
dpo/evaluation/backup/ensemble copy.py
dpo/evaluation/backup/estimators copy.py
dpo/examples/__init__.py
dpo/examples/advanced_config.py
dpo/examples/basic_usage copy.py
dpo/examples/basic_usage.py
dpo/examples/benchmark.py
dpo/examples/benchmark_claude.py
dpo/examples/benchmark_population.py
dpo/examples/benchmark_single.py
dpo/examples/comparative_analysis.py
dpo/examples/compare.py
dpo/examples/custom_estimator.py
dpo/examples/prof_cost.py
dpo/examples/professional.py
dpo/examples/professional_benchmark.py
dpo/examples/working_benchmark.py
dpo/utils/__init__.py
dpo/utils/helpers.py
dpo/utils/io.py
dpo/utils/logger.py
dpo-1.5.0.dist-info/licenses/LICENSE
tests/__init__.py
tests/test_benchmarks.py
tests/test_estimators.py
tests/test_gene.py
tests/test_integration.py
tests/test_optimizer.py
dpo-1.5.0.dist-info/METADATA
dpo-1.5.0.dist-info/WHEEL
dpo-1.5.0.dist-info/entry_points.txt
dpo-1.5.0.dist-info/top_level.txt
dpo-1.5.0.dist-info/RECORD
