Metadata-Version: 2.4
Name: dpo
Version: 1.5.0
Summary: DPO Neural Architecture Search
Author-email: Arya H <arya.h1718@gmail.com>
License: MIT
Project-URL: Homepage, https://github.com/Arya1718/dpo
Project-URL: Repository, https://github.com/Arya1718/dpo
Project-URL: Documentation, https://dpo-nas.readthedocs.io/
Project-URL: Issues, https://github.com/Arya1718/dpo/issues
Classifier: Development Status :: 4 - Beta
Classifier: Intended Audience :: Developers
Classifier: Intended Audience :: Science/Research
Classifier: License :: OSI Approved :: MIT License
Classifier: Programming Language :: Python :: 3
Classifier: Programming Language :: Python :: 3.8
Classifier: Programming Language :: Python :: 3.9
Classifier: Programming Language :: Python :: 3.10
Classifier: Programming Language :: Python :: 3.11
Classifier: Topic :: Scientific/Engineering :: Artificial Intelligence
Classifier: Topic :: Software Development :: Libraries :: Python Modules
Requires-Python: >=3.8
License-File: LICENSE
Requires-Dist: numpy>=1.21.0
Provides-Extra: benchmarks
Requires-Dist: nasbench>=1.0; extra == "benchmarks"
Requires-Dist: nas-bench-x11>=2.0; extra == "benchmarks"
Requires-Dist: nasbench301>=0.2; extra == "benchmarks"
Requires-Dist: hpobench>=0.0.8; extra == "benchmarks"
Requires-Dist: nats-bench>=1.0; extra == "benchmarks"
Provides-Extra: dev
Requires-Dist: pytest>=6.0; extra == "dev"
Requires-Dist: black>=21.0; extra == "dev"
Requires-Dist: flake8>=3.9; extra == "dev"
Requires-Dist: mypy>=0.910; extra == "dev"
Provides-Extra: docs
Requires-Dist: sphinx>=4.0; extra == "docs"
Requires-Dist: sphinx-rtd-theme>=1.0; extra == "docs"
Provides-Extra: gpu
Requires-Dist: torch>=1.9.0; extra == "gpu"
Dynamic: license-file
